EcoSpace/E-Ari.py
EcoSpace/Math.py
EcoSpace/Web.py
EcoSpace/Window.py
EcoSpace/__init__.py
EcoSpace-0.0.4.dist-info/METADATA
EcoSpace-0.0.4.dist-info/WHEEL
EcoSpace-0.0.4.dist-info/top_level.txt
EcoSpace-0.0.4.dist-info/RECORD
