Metadata-Version: 2.1
Name: EcoSpace
Version: 0.0.4
Summary: EcoSpace官方库
Home-page: UNKNOWN
Author: EcoSpace
Author-email: getmail@ecospace.top
License: UNKNOWN
Platform: UNKNOWN
